ROCFunctions/ROCFunctions.py
ROCFunctions/__init__.py
ROCFunctions-0.1.2.dist-info/LICENSE
ROCFunctions-0.1.2.dist-info/METADATA
ROCFunctions-0.1.2.dist-info/WHEEL
ROCFunctions-0.1.2.dist-info/top_level.txt
ROCFunctions-0.1.2.dist-info/RECORD
